[{"city":"Ljubljana - dostava","region":"46.0511","cords":"46.0511,14.5051"},{"city":"Ljubljana - poštni predali","region":"46.0511","cords":"46.0511,14.5051"},{"city":"Ljubljana Šentvid","region":"46.0964","cords":"46.0964,14.4697"},{"city":"Ljubljana-Šmartno","region":"46.168","cords":"46.168,14.5217"},{"city":"Medvode","region":"46.1333","cords":"46.1333,14.4333"},{"city":"Smlednik","region":"46.1642","cords":"46.1642,14.4325"},{"city":"Vodice","region":"46.1899","cords":"46.1899,14.4949"},{"city":"Komenda","region":"46.2048","cords":"46.2048,14.5384"},{"city":"Laze v Tuhinju","region":"46.2194","cords":"46.2194,14.7611"},{"city":"Motnik","region":"46.2153","cords":"46.2153,14.8911"},{"city":"Trojane","region":"46.1883","cords":"46.1883,14.8831"},{"city":"Blagovica","region":"46.1769","cords":"46.1769,14.8072"},{"city":"Lukovica","region":"46.1667","cords":"46.1667,14.7"},{"city":"Domžale","region":"46.1377","cords":"46.1377,14.5937"},{"city":"Ljubljana Črnuče","region":"46.1527","cords":"46.1527,14.5952"},{"city":"Dob","region":"46.1519","cords":"46.1519,14.6286"},{"city":"Mengeš","region":"46.1669","cords":"46.1669,14.575"},{"city":"Radomlje","region":"46.1736","cords":"46.1736,14.6122"},{"city":"Trzin","region":"46.1333","cords":"46.1333,14.5667"},{"city":"Kamnik","region":"46.2259","cords":"46.2259,14.6121"},{"city":"Stahovica","region":"46.2619","cords":"46.2619,14.6022"},{"city":"Moravče","region":"46.1369","cords":"46.1369,14.745"},{"city":"Vače","region":"46.12","cords":"46.12,14.8392"},{"city":"Ljubljana Polje","region":"46.0667","cords":"46.0667,14.5833"},{"city":"Ljubljana-Dobrunje","region":"46.0333","cords":"46.0333,14.5833"},{"city":"Dol pri Ljubljani","region":"46.0886","cords":"46.0886,14.6008"},{"city":"Litija","region":"46.0586","cords":"46.0586,14.8225"},{"city":"Polšnik","region":"46.0667","cords":"46.0667,14.95"},{"city":"Dole pri Litiji","region":"46.0353","cords":"46.0353,15.0189"},{"city":"Gabrovka","region":"46.0167","cords":"46.0167,15"},{"city":"Šmartno pri Litiji","region":"46.0444","cords":"46.0444,14.8442"},{"city":"Primskovo","region":"45.9717","cords":"45.9717,14.9104"},{"city":"Kresnice","region":"46.102","cords":"46.102,14.7858"},{"city":"Sava","region":"46.0898","cords":"46.0898,14.8904"},{"city":"Grosuplje","region":"45.9556","cords":"45.9556,14.6589"},{"city":"Škofljica","region":"45.9833","cords":"45.9833,14.5767"},{"city":"Ig","region":"45.9603","cords":"45.9603,14.5289"},{"city":"Šmarje-Sap","region":"45.9762","cords":"45.9762,14.6118"},{"city":"Višnja Gora","region":"45.9539","cords":"45.9539,14.7453"},{"city":"Ivančna Gorica","region":"45.9383","cords":"45.9383,14.8044"},{"city":"Šentvid pri Stični","region":"45.95","cords":"45.95,14.8434"},{"city":"Krka","region":"45.8813","cords":"45.8813,14.7781"},{"city":"Zagradec","region":"45.8614","cords":"45.8614,14.8342"},{"city":"Ribnica","region":"45.7386","cords":"45.7386,14.7275"},{"city":"Turjak","region":"45.8789","cords":"45.8789,14.6153"},{"city":"Videm-Dobrepolje","region":"45.85","cords":"45.85,14.6942"},{"city":"Struge","region":"45.7817","cords":"45.7817,14.7747"},{"city":"Rob","region":"45.8486","cords":"45.8486,14.5722"},{"city":"Velike Lašče","region":"45.8322","cords":"45.8322,14.6364"},{"city":"Ortnek","region":"45.782","cords":"45.782,14.6753"},{"city":"Sodražica","region":"45.7611","cords":"45.7611,14.6356"},{"city":"Loški Potok","region":"45.8236","cords":"45.8236,14.6531"},{"city":"Draga","region":"45.9395","cords":"45.9395,14.547"},{"city":"Kočevje","region":"45.6433","cords":"45.6433,14.8633"},{"city":"Dolenja vas","region":"45.7061","cords":"45.7061,14.7544"},{"city":"Stara Cerkev","region":"45.6722","cords":"45.6722,14.8397"},{"city":"Vas","region":"45.4747","cords":"45.4747,14.8692"},{"city":"Osilnica","region":"45.5278","cords":"45.5278,14.6944"},{"city":"Kočevska Reka","region":"45.5764","cords":"45.5764,14.7969"},{"city":"Brezovica pri Ljubljani","region":"46.0333","cords":"46.0333,14.4"},{"city":"Preserje","region":"45.9569","cords":"45.9569,14.4189"},{"city":"Borovnica","region":"45.9158","cords":"45.9158,14.3631"},{"city":"Horjul","region":"46.0236","cords":"46.0236,14.2992"},{"city":"Polhov Gradec","region":"46.0669","cords":"46.0669,14.3161"},{"city":"Dobrova","region":"46.055","cords":"46.055,14.4172"},{"city":"Notranje Gorice","region":"45.9875","cords":"45.9875,14.3989"},{"city":"Log pri Brezovici","region":"46.0167","cords":"46.0167,14.3667"},{"city":"Vrhnika","region":"45.6922","cords":"45.6922,14.5028"},{"city":"Logatec","region":"45.9144","cords":"45.9144,14.2258"},{"city":"Logatec","region":"45.9144","cords":"45.9144,14.2258"},{"city":"Hotedršica","region":"45.9303","cords":"45.9303,14.1422"},{"city":"Rovte","region":"45.9853","cords":"45.9853,14.1775"},{"city":"Cerknica","region":"45.7931","cords":"45.7931,14.3625"},{"city":"Rakek","region":"45.8133","cords":"45.8133,14.3111"},{"city":"Begunje pri Cerknici","region":"45.8181","cords":"45.8181,14.3822"},{"city":"Grahovo","region":"45.7692","cords":"45.7692,14.4222"},{"city":"Nova vas","region":"45.7717","cords":"45.7717,14.5058"},{"city":"Stari trg pri Ložu","region":"45.7148","cords":"45.7148,14.471"},{"city":"Zagorje ob Savi","region":"46.1318","cords":"46.1318,14.9969"},{"city":"Izlake","region":"46.15","cords":"46.15,14.95"},{"city":"Kisovec","region":"46.1391","cords":"46.1391,14.9629"},{"city":"Čemšenik","region":"46.1792","cords":"46.1792,14.9444"},{"city":"Podkum","region":"46.0714","cords":"46.0714,15.0286"},{"city":"Trbovlje","region":"46.155","cords":"46.155,15.0533"},{"city":"Dobovec","region":"46.1131","cords":"46.1131,15.0572"},{"city":"Hrastnik","region":"46.1461","cords":"46.1461,15.0814"},{"city":"Dol pri Hrastniku","region":"46.1419","cords":"46.1419,15.1128"},{"city":"Zidani Most","region":"46.0882","cords":"46.0882,15.1728"},{"city":"Radeče","region":"46.0681","cords":"46.0681,15.1839"},{"city":"Loka pri Zidanem Mostu","region":"46.0575","cords":"46.0575,15.2072"},{"city":"Ljubljana","region":"46.0511","cords":"46.0511,14.5051"},{"city":"Ljubljana","region":"46.0511","cords":"46.0511,14.5051"},{"city":"Ljubljana","region":"46.0511","cords":"46.0511,14.5051"},{"city":"Ljubljana","region":"46.0511","cords":"46.0511,14.5051"},{"city":"Ljubljana","region":"46.0511","cords":"46.0511,14.5051"},{"city":"Ljubljana","region":"46.0511","cords":"46.0511,14.5051"},{"city":"Ljubljana","region":"46.0511","cords":"46.0511,14.5051"},{"city":"Ljubljana","region":"46.0511","cords":"46.0511,14.5051"},{"city":"Ljubljana","region":"46.0511","cords":"46.0511,14.5051"},{"city":"Ljubljana","region":"46.0511","cords":"46.0511,14.5051"},{"city":"Ljubljana","region":"46.0511","cords":"46.0511,14.5051"},{"city":"Ljubljana","region":"46.0511","cords":"46.0511,14.5051"},{"city":"Ljubljana","region":"46.0511","cords":"46.0511,14.5051"},{"city":"Ljubljana","region":"46.0511","cords":"46.0511,14.5051"},{"city":"Ljubljana","region":"46.0511","cords":"46.0511,14.5051"},{"city":"Ljubljana","region":"46.0511","cords":"46.0511,14.5051"},{"city":"Ljubljana","region":"46.0511","cords":"46.0511,14.5051"},{"city":"Ljubljana","region":"46.0511","cords":"46.0511,14.5051"},{"city":"Ljubljana","region":"46.0511","cords":"46.0511,14.5051"},{"city":"Ljubljana","region":"46.0511","cords":"46.0511,14.5051"},{"city":"Ljubljana","region":"46.0511","cords":"46.0511,14.5051"},{"city":"Ljubljana","region":"46.0511","cords":"46.0511,14.5051"},{"city":"Ljubljana","region":"46.0511","cords":"46.0511,14.5051"},{"city":"Ljubljana","region":"46.0511","cords":"46.0511,14.5051"},{"city":"Ljubljana","region":"46.0511","cords":"46.0511,14.5051"},{"city":"Ljubljana","region":"46.0511","cords":"46.0511,14.5051"},{"city":"Ljubljana","region":"46.0511","cords":"46.0511,14.5051"},{"city":"Ljubljana","region":"46.0511","cords":"46.0511,14.5051"},{"city":"Ljubljana","region":"46.0511","cords":"46.0511,14.5051"},{"city":"Ljubljana","region":"46.0511","cords":"46.0511,14.5051"},{"city":"Ljubljana","region":"46.0511","cords":"46.0511,14.5051"},{"city":"Ljubljana","region":"46.0511","cords":"46.0511,14.5051"},{"city":"Ljubljana","region":"46.0511","cords":"46.0511,14.5051"},{"city":"Ljubljana","region":"46.0511","cords":"46.0511,14.5051"},{"city":"Ljubljana","region":"46.0511","cords":"46.0511,14.5051"},{"city":"Ljubljana","region":"46.0511","cords":"46.0511,14.5051"},{"city":"Ljubljana","region":"46.0511","cords":"46.0511,14.5051"},{"city":"Ljubljana","region":"46.0511","cords":"46.0511,14.5051"},{"city":"Ljubljana","region":"46.0511","cords":"46.0511,14.5051"},{"city":"Ljubljana","region":"46.0511","cords":"46.0511,14.5051"},{"city":"Ljubljana","region":"46.0511","cords":"46.0511,14.5051"},{"city":"Ljubljana","region":"46.0511","cords":"46.0511,14.5051"},{"city":"Ljubljana","region":"46.0511","cords":"46.0511,14.5051"},{"city":"Ljubljana","region":"46.0511","cords":"46.0511,14.5051"},{"city":"Ljubljana","region":"46.0511","cords":"46.0511,14.5051"},{"city":"Maribor - dostava","region":"46.5547","cords":"46.5547,15.6467"},{"city":"Maribor - poštni predali","region":"46.5547","cords":"46.5547,15.6467"},{"city":"Zgornja Kungota","region":"46.6392","cords":"46.6392,15.6156"},{"city":"Miklavž na Dravskem polju","region":"46.5058","cords":"46.5058,15.6972"},{"city":"Starše","region":"46.4658","cords":"46.4658,15.7672"},{"city":"Marjeta na Dravskem polju","region":"46.4525","cords":"46.4525,15.7369"},{"city":"Pohorje","region":"46.5026","cords":"46.5026,15.573"},{"city":"Pesnica pri Mariboru","region":"46.6069","cords":"46.6069,15.6767"},{"city":"Šentilj v Slovenskih goricah","region":"46.6792","cords":"46.6792,15.6532"},{"city":"Zgornja Velka","region":"46.6753","cords":"46.6753,15.7692"},{"city":"Sladki Vrh","region":"46.7075","cords":"46.7075,15.8011"},{"city":"Ceršak","region":"46.6992","cords":"46.6992,15.6692"},{"city":"Jarenina","region":"46.5803","cords":"46.5803,15.7438"},{"city":"Jakobski Dol","region":"46.5803","cords":"46.5803,15.7438"},{"city":"Jurovski Dol","region":"46.6064","cords":"46.6064,15.7847"},{"city":"Malečnik","region":"46.5542","cords":"46.5542,15.7028"},{"city":"Lenart v Slovenskih goricah","region":"46.5761","cords":"46.5761,15.8314"},{"city":"Pernica","region":"46.58","cords":"46.58,15.7278"},{"city":"Voličina","region":"46.5838","cords":"46.5838,15.8478"},{"city":"Sv. Ana v Slovenskih goricah","region":"46.5838","cords":"46.5838,15.8478"},{"city":"Benedikt","region":"46.6086","cords":"46.6086,15.8883"},{"city":"Sv. Trojica v Slovenskih goricah","region":"46.5838","cords":"46.5838,15.8478"},{"city":"Cerkvenjak","region":"46.5706","cords":"46.5706,15.9436"},{"city":"Spodnji Duplek","region":"46.5031","cords":"46.5031,15.7453"},{"city":"Zgornja Korena","region":"46.524","cords":"46.524,15.7723"},{"city":"Ptuj","region":"46.4201","cords":"46.4201,15.8702"},{"city":"Dornava","region":"46.4367","cords":"46.4367,15.9536"},{"city":"Destrnik","region":"46.5006","cords":"46.5006,15.875"},{"city":"Trnovska vas","region":"46.5202","cords":"46.5202,15.8866"},{"city":"Vitomarci","region":"46.5275","cords":"46.5275,15.9394"},{"city":"Juršinci","region":"46.4847","cords":"46.4847,15.9714"},{"city":"Polenšak","region":"46.4746","cords":"46.4746,16.0031"},{"city":"Sveti Tomaž","region":"46.4842","cords":"46.4842,16.0836"},{"city":"Ivanjkovci","region":"46.4622","cords":"46.4622,16.1458"},{"city":"Ormož","region":"46.4114","cords":"46.4114,16.1544"},{"city":"Gorišnica","region":"46.4147","cords":"46.4147,16.0139"},{"city":"Podgorci","region":"46.4292","cords":"46.4292,16.0636"},{"city":"Velika Nedelja","region":"46.4178","cords":"46.4178,16.1097"},{"city":"Miklavž pri Ormožu","region":"46.46","cords":"46.46,16.2136"},{"city":"Kog","region":"46.4717","cords":"46.4717,16.2508"},{"city":"Središče ob Dravi","region":"46.3942","cords":"46.3942,16.2681"},{"city":"Markovci","region":"46.3833","cords":"46.3833,15.95"},{"city":"Cirkulane","region":"46.3441","cords":"46.3441,15.9947"},{"city":"Zavrč","region":"46.3917","cords":"46.3917,16.0497"},{"city":"Videm pri Ptuju","region":"46.3686","cords":"46.3686,15.9064"},{"city":"Zgornji Leskovec","region":"46.3303","cords":"46.3303,15.9369"},{"city":"Podlehnik","region":"46.3353","cords":"46.3353,15.88"},{"city":"Žetale","region":"46.275","cords":"46.275,15.7939"},{"city":"Hajdina","region":"46.4089","cords":"46.4089,15.8469"},{"city":"Stoperce","region":"46.29","cords":"46.29,15.7167"},{"city":"Slovenska Bistrica","region":"46.3928","cords":"46.3928,15.5744"},{"city":"Hoče","region":"46.4918","cords":"46.4918,15.6231"},{"city":"Orehova vas","region":"46.4701","cords":"46.4701,15.6686"},{"city":"Fram","region":"46.4506","cords":"46.4506,15.6322"},{"city":"Zgornja Polskava","region":"46.4256","cords":"46.4256,15.6122"},{"city":"Šmartno na Pohorju","region":"46.4442","cords":"46.4442,15.5394"},{"city":"Zgornja Ložnica","region":"46.3833","cords":"46.3833,15.5167"},{"city":"Oplotnica","region":"46.3878","cords":"46.3878,15.4467"},{"city":"Laporje","region":"46.3467","cords":"46.3467,15.5947"},{"city":"Poljčane","region":"46.3119","cords":"46.3119,15.5792"},{"city":"Makole","region":"46.3172","cords":"46.3172,15.6672"},{"city":"Majšperk","region":"46.3517","cords":"46.3517,15.7336"},{"city":"Ptujska Gora","region":"46.355","cords":"46.355,15.76"},{"city":"Lovrenc na Dravskem polju","region":"46.3736","cords":"46.3736,15.7792"},{"city":"Kidričevo","region":"46.4036","cords":"46.4036,15.7911"},{"city":"Cirkovce","region":"46.3999","cords":"46.3999,15.7312"},{"city":"Rače","region":"46.4519","cords":"46.4519,15.6814"},{"city":"Pragersko","region":"46.3967","cords":"46.3967,15.66"},{"city":"Limbuš","region":"46.5536","cords":"46.5536,15.5836"},{"city":"Ruše","region":"46.5394","cords":"46.5394,15.5158"},{"city":"Fala","region":"46.5439","cords":"46.5439,15.4472"},{"city":"Lovrenc na Pohorju","region":"46.5406","cords":"46.5406,15.3931"},{"city":"Bistrica ob Dravi","region":"46.5572","cords":"46.5572,15.5144"},{"city":"Kamnica","region":"46.5744","cords":"46.5744,15.6142"},{"city":"Selnica ob Dravi","region":"46.55","cords":"46.55,15.495"},{"city":"Sv. Duh na Ostrem Vrhu","region":"46.5647","cords":"46.5647,15.5614"},{"city":"Bresternica","region":"46.5697","cords":"46.5697,15.575"},{"city":"Radlje ob Dravi","region":"46.6142","cords":"46.6142,15.2264"},{"city":"Ožbalt","region":"46.5869","cords":"46.5869,15.3989"},{"city":"Kapla","region":"46.2483","cords":"46.2483,15.0094"},{"city":"Podvelka","region":"46.5869","cords":"46.5869,15.3306"},{"city":"Ribnica na Pohorju","region":"46.535","cords":"46.535,15.2728"},{"city":"Vuhred","region":"46.5947","cords":"46.5947,15.2375"},{"city":"Muta","region":"46.6114","cords":"46.6114,15.1661"},{"city":"Vuzenica","region":"46.5964","cords":"46.5964,15.1672"},{"city":"Dravograd","region":"46.5881","cords":"46.5881,15.0192"},{"city":"Trbonje","region":"46.6028","cords":"46.6028,15.1075"},{"city":"Libeliče","region":"46.62","cords":"46.62,14.9497"},{"city":"Šentjanž pri Dravogradu","region":"46.5611","cords":"46.5611,15.0389"},{"city":"Slovenj Gradec","region":"46.5103","cords":"46.5103,15.0806"},{"city":"Podgorje pri Slovenj Gradcu","region":"46.4719","cords":"46.4719,15.0836"},{"city":"Mislinja","region":"46.4411","cords":"46.4411,15.1956"},{"city":"Šmartno pri Slovenj Gradcu","region":"46.4894","cords":"46.4894,15.1067"},{"city":"Ravne na Koroškem","region":"46.5431","cords":"46.5431,14.9692"},{"city":"Prevalje","region":"46.5469","cords":"46.5469,14.9208"},{"city":"Mežica","region":"46.5214","cords":"46.5214,14.8544"},{"city":"Črna na Koroškem","region":"46.4705","cords":"46.4705,14.8501"},{"city":"Kotlje","region":"46.5214","cords":"46.5214,14.9869"},{"city":"Maribor","region":"46.5547","cords":"46.5547,15.6467"},{"city":"Maribor","region":"46.5547","cords":"46.5547,15.6467"},{"city":"Maribor","region":"46.5547","cords":"46.5547,15.6467"},{"city":"Maribor","region":"46.5547","cords":"46.5547,15.6467"},{"city":"Maribor","region":"46.5547","cords":"46.5547,15.6467"},{"city":"Maribor","region":"46.5547","cords":"46.5547,15.6467"},{"city":"Maribor","region":"46.5547","cords":"46.5547,15.6467"},{"city":"Maribor","region":"46.5547","cords":"46.5547,15.6467"},{"city":"Maribor","region":"46.5547","cords":"46.5547,15.6467"},{"city":"Maribor","region":"46.5547","cords":"46.5547,15.6467"},{"city":"Maribor","region":"46.5547","cords":"46.5547,15.6467"},{"city":"Maribor","region":"46.5547","cords":"46.5547,15.6467"},{"city":"Maribor","region":"46.5547","cords":"46.5547,15.6467"},{"city":"Celje - dostava","region":"45.5916","cords":"45.5916,14.1546"},{"city":"Celje - poštni predali","region":"45.5916","cords":"45.5916,14.1546"},{"city":"Šmartno v Rožni dolini","region":"46.2945","cords":"46.2945,15.2431"},{"city":"Ljubečna","region":"46.2417","cords":"46.2417,15.3208"},{"city":"Nova Cerkev","region":"46.3128","cords":"46.3128,15.2856"},{"city":"Dobrna","region":"46.3375","cords":"46.3375,15.2264"},{"city":"Vitanje","region":"46.3817","cords":"46.3817,15.2958"},{"city":"Stranice","region":"46.3636","cords":"46.3636,15.3653"},{"city":"Slovenske Konjice","region":"46.3367","cords":"46.3367,15.4258"},{"city":"Škofja vas","region":"46.2679","cords":"46.2679,15.2912"},{"city":"Vojnik","region":"46.2933","cords":"46.2933,15.3033"},{"city":"Frankolovo","region":"46.3306","cords":"46.3306,15.3144"},{"city":"Zreče","region":"46.3822","cords":"46.3822,15.3792"},{"city":"Loče","region":"46.283","cords":"46.283,15.258"},{"city":"Štore","region":"46.2208","cords":"46.2208,15.3139"},{"city":"Teharje","region":"46.2303","cords":"46.2303,15.3022"},{"city":"Dramlje","region":"46.2736","cords":"46.2736,15.3947"},{"city":"Loka pri Žusmu","region":"46.1575","cords":"46.1575,15.5147"},{"city":"Dobje pri Planini","region":"46.1367","cords":"46.1367,15.4089"},{"city":"Planina pri Sevnici","region":"46.1114","cords":"46.1114,15.4094"},{"city":"Šentjur","region":"46.2172","cords":"46.2172,15.3975"},{"city":"Grobelno","region":"46.2117","cords":"46.2117,15.4447"},{"city":"Ponikva","region":"46.241","cords":"46.241,15.4567"},{"city":"Kalobje","region":"46.1672","cords":"46.1672,15.3944"},{"city":"Šmarje pri Jelšah","region":"46.2272","cords":"46.2272,15.5192"},{"city":"Podplat","region":"46.2461","cords":"46.2461,15.5764"},{"city":"Rogaška Slatina","region":"46.2375","cords":"46.2375,15.6397"},{"city":"Rogatec","region":"46.2294","cords":"46.2294,15.7003"},{"city":"Pristava pri Mestinju","region":"46.1967","cords":"46.1967,15.5961"},{"city":"Podčetrtek","region":"46.1569","cords":"46.1569,15.5986"},{"city":"Buče","region":"46.1079","cords":"46.1079,15.5701"},{"city":"Bistrica ob Sotli","region":"46.0589","cords":"46.0589,15.6642"},{"city":"Podsreda","region":"46.0414","cords":"46.0414,15.5906"},{"city":"Kozje","region":"46.075","cords":"46.075,15.5603"},{"city":"Lesično","region":"46.1025","cords":"46.1025,15.5142"},{"city":"Prevorje","region":"46.1255","cords":"46.1255,15.4774"},{"city":"Gorica pri Slivnici","region":"46.1872","cords":"46.1872,15.4325"},{"city":"Sveti Štefan","region":"46.1862","cords":"46.1862,15.4933"},{"city":"Laško","region":"46.1546","cords":"46.1546,15.2355"},{"city":"Šentrupert","region":"46.1714","cords":"46.1714,15.3494"},{"city":"Rimske Toplice","region":"46.1226","cords":"46.1226,15.1919"},{"city":"Jurklošter","region":"46.0917","cords":"46.0917,15.3367"},{"city":"Petrovče","region":"46.2417","cords":"46.2417,15.19"},{"city":"Griže","region":"46.2294","cords":"46.2294,15.1506"},{"city":"Gomilsko","region":"46.2528","cords":"46.2528,15.0422"},{"city":"Tabor","region":"46.2361","cords":"46.2361,15.0183"},{"city":"Vransko","region":"46.2439","cords":"46.2439,14.9514"},{"city":"Žalec","region":"46.2515","cords":"46.2515,15.1648"},{"city":"Šempeter v Savinjski dolini","region":"46.2654","cords":"46.2654,15.0907"},{"city":"Prebold","region":"46.2369","cords":"46.2369,15.0925"},{"city":"Polzela","region":"46.2833","cords":"46.2833,15.0667"},{"city":"Braslovče","region":"46.2897","cords":"46.2897,15.0389"},{"city":"Velenje - dostava","region":"46.3712","cords":"46.3712,15.0345"},{"city":"Velenje - poštni predali","region":"46.3712","cords":"46.3712,15.0345"},{"city":"Šoštanj","region":"46.38","cords":"46.38,15.0486"},{"city":"Topolšica","region":"46.4003","cords":"46.4003,15.0216"},{"city":"Šmartno ob Paki","region":"46.3333","cords":"46.3333,15.0333"},{"city":"Mozirje","region":"46.3394","cords":"46.3394,14.9633"},{"city":"Nazarje","region":"46.3176","cords":"46.3176,14.9467"},{"city":"Rečica ob Savinji","region":"46.3167","cords":"46.3167,14.9167"},{"city":"Ljubno ob Savinji","region":"46.3436","cords":"46.3436,14.8338"},{"city":"Luče","region":"46.3561","cords":"46.3561,14.7467"},{"city":"Solčava","region":"46.4194","cords":"46.4194,14.6936"},{"city":"Šmartno ob Dreti","region":"46.2839","cords":"46.2839,14.8903"},{"city":"Gornji Grad","region":"46.2953","cords":"46.2953,14.8083"},{"city":"Celje","region":"46.2309","cords":"46.2309,15.2604"},{"city":"Velenje","region":"46.3592","cords":"46.3592,15.1103"},{"city":"Velenje","region":"46.3592","cords":"46.3592,15.1103"},{"city":"Celje","region":"46.2309","cords":"46.2309,15.2604"},{"city":"Celje","region":"46.2309","cords":"46.2309,15.2604"},{"city":"Kranj - dostava","region":"46.2389","cords":"46.2389,14.3556"},{"city":"Kranj - poštni predali","region":"46.2389","cords":"46.2389,14.3556"},{"city":"Zgornja Besnica","region":"46.2667","cords":"46.2667,14.2833"},{"city":"Naklo","region":"46.2728","cords":"46.2728,14.3172"},{"city":"Duplje","region":"46.2821","cords":"46.2821,14.3831"},{"city":"Golnik","region":"46.3333","cords":"46.3333,14.3333"},{"city":"Preddvor","region":"46.3025","cords":"46.3025,14.4231"},{"city":"Zgornje Jezersko","region":"46.3833","cords":"46.3833,14.4667"},{"city":"Cerklje na Gorenjskem","region":"46.2542","cords":"46.2542,14.4886"},{"city":"Šenčur","region":"46.2456","cords":"46.2456,14.4197"},{"city":"Žabnica","region":"46.1986","cords":"46.1986,14.3331"},{"city":"Brnik aerodrom","region":"46.2264","cords":"46.2264,14.4064"},{"city":"Mavčiče","region":"46.1818","cords":"46.1818,14.3948"},{"city":"Visoko","region":"46.2711","cords":"46.2711,14.4181"},{"city":"Škofja Loka","region":"46.1655","cords":"46.1655,14.3063"},{"city":"Poljane nad Škofjo Loko","region":"46.121","cords":"46.121,14.1862"},{"city":"Gorenja vas","region":"46.1667","cords":"46.1667,14.15"},{"city":"Sovodenj","region":"46.0864","cords":"46.0864,14.0436"},{"city":"Žiri","region":"46.0422","cords":"46.0422,14.1072"},{"city":"Selca","region":"46.2244","cords":"46.2244,14.2056"},{"city":"Železniki","region":"46.2333","cords":"46.2333,14.1667"},{"city":"Sorica","region":"46.2167","cords":"46.2167,14.0333"},{"city":"Radovljica","region":"46.3444","cords":"46.3444,14.1744"},{"city":"Brezje","region":"46.329","cords":"46.329,14.2323"},{"city":"Podnart","region":"46.2952","cords":"46.2952,14.2557"},{"city":"Kropa","region":"46.3","cords":"46.3,14.2"},{"city":"Kamna Gorica","region":"46.3167","cords":"46.3167,14.2"},{"city":"Zgornje Gorje","region":"46.3796","cords":"46.3796,14.0694"},{"city":"Lesce","region":"46.3611","cords":"46.3611,14.1578"},{"city":"Bled","region":"46.3692","cords":"46.3692,14.1136"},{"city":"Bohinjska Bela","region":"46.3489","cords":"46.3489,14.0639"},{"city":"Bohinjska Bistrica","region":"46.2722","cords":"46.2722,13.9535"},{"city":"Bohinjsko jezero","region":"46.3218","cords":"46.3218,14.0141"},{"city":"Srednja vas v Bohinju","region":"46.297","cords":"46.297,13.9256"},{"city":"Jesenice","region":"46.4306","cords":"46.4306,14.0669"},{"city":"Blejska Dobrava","region":"46.4","cords":"46.4,14.1"},{"city":"Žirovnica","region":"46.4047","cords":"46.4047,14.14"},{"city":"Begunje na Gorenjskem","region":"46.3833","cords":"46.3833,14.2167"},{"city":"Hrušica","region":"46.445","cords":"46.445,14.0178"},{"city":"Kranjska Gora","region":"46.4839","cords":"46.4839,13.7894"},{"city":"Mojstrana","region":"46.4611","cords":"46.4611,13.9369"},{"city":"Gozd Martuljek","region":"46.4833","cords":"46.4833,13.8333"},{"city":"Rateče-Planica","region":"46.4761","cords":"46.4761,13.8532"},{"city":"Tržič","region":"46.3636","cords":"46.3636,14.3105"},{"city":"Križe","region":"46.3428","cords":"46.3428,14.3014"},{"city":"Naklo","region":"46.2728","cords":"46.2728,14.3172"},{"city":"Kranj","region":"46.2389","cords":"46.2389,14.3556"},{"city":"Kranj","region":"46.2389","cords":"46.2389,14.3556"},{"city":"Nova Gorica - dostava","region":"45.958","cords":"45.958,13.6469"},{"city":"Nova Gorica - poštni predali","region":"45.9431","cords":"45.9431,13.6393"},{"city":"Deskle","region":"46.0531","cords":"46.0531,13.6138"},{"city":"Kojsko","region":"46.0092","cords":"46.0092,13.5797"},{"city":"Dobrovo v Brdih","region":"45.9964","cords":"45.9964,13.5264"},{"city":"Kanal","region":"46.0886","cords":"46.0886,13.6397"},{"city":"Kal nad Kanalom","region":"46.0833","cords":"46.0833,13.7403"},{"city":"Ročinj","region":"46.1128","cords":"46.1128,13.67"},{"city":"Most na Soči","region":"46.1469","cords":"46.1469,13.7389"},{"city":"Tolmin","region":"46.183","cords":"46.183,13.7332"},{"city":"Kobarid","region":"46.2481","cords":"46.2481,13.5772"},{"city":"Breginj","region":"46.2647","cords":"46.2647,13.4278"},{"city":"Srpenica","region":"46.2917","cords":"46.2917,13.4988"},{"city":"Bovec","region":"46.3375","cords":"46.3375,13.5528"},{"city":"Log pod Mangartom","region":"46.4019","cords":"46.4019,13.5969"},{"city":"Soča","region":"46.3433","cords":"46.3433,13.6564"},{"city":"Grahovo ob Bači","region":"46.1539","cords":"46.1539,13.8619"},{"city":"Podbrdo","region":"46.21","cords":"46.21,13.9644"},{"city":"Solkan","region":"45.9714","cords":"45.9714,13.6494"},{"city":"Grgar","region":"45.9986","cords":"45.9986,13.6739"},{"city":"Trnovo pri Gorici","region":"45.9742","cords":"45.9742,13.7433"},{"city":"Čepovan","region":"46.0494","cords":"46.0494,13.7969"},{"city":"Šempas","region":"45.9303","cords":"45.9303,13.7436"},{"city":"Črniče","region":"45.9106","cords":"45.9106,13.7767"},{"city":"Dobravlje","region":"45.8839","cords":"45.8839,13.8453"},{"city":"Ajdovščina","region":"45.886","cords":"45.886,13.9095"},{"city":"Vipava","region":"45.8467","cords":"45.8467,13.9631"},{"city":"Podnanos","region":"45.7969","cords":"45.7969,13.9714"},{"city":"Col","region":"45.8758","cords":"45.8758,14.005"},{"city":"Črni Vrh nad Idrijo","region":"45.8726","cords":"45.8726,13.9885"},{"city":"Godovič","region":"45.9578","cords":"45.9578,14.0936"},{"city":"Idrija","region":"46.0028","cords":"46.0028,14.0306"},{"city":"Spodnja Idrija","region":"46.0319","cords":"46.0319,14.0272"},{"city":"Cerkno","region":"46.1256","cords":"46.1256,13.9817"},{"city":"Slap ob Idrijci","region":"46.1233","cords":"46.1233,13.8047"},{"city":"Šempeter pri Gorici","region":"45.9275","cords":"45.9275,13.6411"},{"city":"Miren","region":"45.8956","cords":"45.8956,13.6075"},{"city":"Renče","region":"45.89","cords":"45.89,13.6686"},{"city":"Volčja Draga","region":"45.9069","cords":"45.9069,13.6775"},{"city":"Dornberk","region":"45.8897","cords":"45.8897,13.7369"},{"city":"Branik","region":"45.8572","cords":"45.8572,13.7842"},{"city":"Kostanjevica na Krasu","region":"45.845","cords":"45.845,13.6417"},{"city":"Prvačina","region":"45.89","cords":"45.89,13.7181"},{"city":"Nova Gorica","region":"45.956","cords":"45.956,13.6484"},{"city":"Koper/Capodistria - dostava","region":"45.5538","cords":"45.5538,13.7439"},{"city":"Koper/Capodistria - poštni predali","region":"45.5472","cords":"45.5472,13.7258"},{"city":"Sežana","region":"45.7092","cords":"45.7092,13.8733"},{"city":"Divača","region":"45.6847","cords":"45.6847,13.9703"},{"city":"Podgorje","region":"45.5292","cords":"45.5292,13.9528"},{"city":"Vremski Britof","region":"45.6571","cords":"45.6571,14.0301"},{"city":"Lokev","region":"45.6611","cords":"45.6611,13.9281"},{"city":"Dutovlje","region":"45.7581","cords":"45.7581,13.8322"},{"city":"Štanjel","region":"45.8233","cords":"45.8233,13.8436"},{"city":"Komen","region":"45.8153","cords":"45.8153,13.7483"},{"city":"Senožeče","region":"45.7211","cords":"45.7211,14.0411"},{"city":"Hruševje","region":"45.7606","cords":"45.7606,14.1064"},{"city":"Postojna","region":"45.7769","cords":"45.7769,14.2167"},{"city":"Planina","region":"45.8339","cords":"45.8339,14.2561"},{"city":"Kozina","region":"45.61","cords":"45.61,13.9356"},{"city":"Materija","region":"45.5814","cords":"45.5814,13.9967"},{"city":"Obrov","region":"45.5425","cords":"45.5425,14.0869"},{"city":"Podgrad","region":"45.5217","cords":"45.5217,14.1461"},{"city":"Ilirska Bistrica","region":"45.5697","cords":"45.5697,14.2408"},{"city":"Ilirska Bistrica-Trnovo","region":"45.6192","cords":"45.6192,14.2205"},{"city":"Knežak","region":"45.6245","cords":"45.6245,14.2448"},{"city":"Jelšane","region":"45.5028","cords":"45.5028,14.2717"},{"city":"Prem","region":"45.6048","cords":"45.6048,14.1834"},{"city":"Košana","region":"45.6192","cords":"45.6192,14.2205"},{"city":"Pivka","region":"45.6829","cords":"45.6829,14.1959"},{"city":"Prestranek","region":"45.7303","cords":"45.7303,14.1862"},{"city":"Dekani","region":"45.5497","cords":"45.5497,13.8136"},{"city":"Gračišče","region":"45.505","cords":"45.505,13.8769"},{"city":"Marezige","region":"45.5097","cords":"45.5097,13.8031"},{"city":"Šmarje","region":"45.5014","cords":"45.5014,13.7178"},{"city":"Črni Kal","region":"45.55","cords":"45.55,13.88"},{"city":"Pobegi","region":"45.5394","cords":"45.5394,13.7961"},{"city":"Ankaran/Ancarano","region":"45.5664","cords":"45.5664,13.7994"},{"city":"Škofije","region":"45.5664","cords":"45.5664,13.7994"},{"city":"Izola/Isola","region":"45.4955","cords":"45.4955,13.6077"},{"city":"Portorož/Portorose","region":"45.5143","cords":"45.5143,13.5921"},{"city":"Strunjan/Strugnano (sezonska pošta)","region":"45.5143","cords":"45.5143,13.5921"},{"city":"Piran/Pirano","region":"45.4767","cords":"45.4767,13.6233"},{"city":"Sečovlje/Sicciole","region":"45.4767","cords":"45.4767,13.6233"},{"city":"Koper","region":"45.5469","cords":"45.5469,13.7294"},{"city":"Koper","region":"45.5469","cords":"45.5469,13.7294"},{"city":"Koper","region":"45.5469","cords":"45.5469,13.7294"},{"city":"Koper","region":"45.5469","cords":"45.5469,13.7294"},{"city":"Koper","region":"45.5469","cords":"45.5469,13.7294"},{"city":"Koper","region":"45.5469","cords":"45.5469,13.7294"},{"city":"Novo mesto - dostava","region":"45.8363","cords":"45.8363,15.1899"},{"city":"Novo mesto - poštni predali","region":"45.8296","cords":"45.8296,15.1997"},{"city":"Trebnje","region":"45.9042","cords":"45.9042,15.0217"},{"city":"Dobrnič","region":"45.875","cords":"45.875,14.98"},{"city":"Velika Loka","region":"45.9289","cords":"45.9289,14.9678"},{"city":"Veliki Gaber","region":"45.9338","cords":"45.9338,14.9071"},{"city":"Mirna Peč","region":"45.8603","cords":"45.8603,15.0833"},{"city":"Šmarješke Toplice","region":"45.8624","cords":"45.8624,15.2219"},{"city":"Otočec","region":"45.8675","cords":"45.8675,15.2733"},{"city":"Mokronog","region":"45.9342","cords":"45.9342,15.1408"},{"city":"Trebelno","region":"45.9167","cords":"45.9167,15.15"},{"city":"Šentrupert","region":"45.9778","cords":"45.9778,15.0956"},{"city":"Mirna","region":"45.9553","cords":"45.9553,15.0619"},{"city":"Brežice","region":"45.9033","cords":"45.9033,15.5911"},{"city":"Čatež ob Savi","region":"45.8894","cords":"45.8894,15.6025"},{"city":"Artiče","region":"45.9539","cords":"45.9539,15.5878"},{"city":"Globoko","region":"45.955","cords":"45.955,15.6286"},{"city":"Pišece","region":"46.0017","cords":"46.0017,15.6411"},{"city":"Sromlje","region":"45.9833","cords":"45.9833,15.6"},{"city":"Dobova","region":"45.8972","cords":"45.8972,15.6637"},{"city":"Kapele","region":"45.9333","cords":"45.9333,15.6833"},{"city":"Bizeljsko","region":"46.0133","cords":"46.0133,15.6967"},{"city":"Jesenice na Dolenjskem","region":"45.8917","cords":"45.8917,15.5397"},{"city":"Krška vas","region":"45.9","cords":"45.9,15.5667"},{"city":"Cerklje ob Krki","region":"45.8834","cords":"45.8834,15.5128"},{"city":"Krško","region":"45.9591","cords":"45.9591,15.4917"},{"city":"Zdole","region":"45.9772","cords":"45.9772,15.5458"},{"city":"Leskovec pri Krškem","region":"45.9357","cords":"45.9357,15.4718"},{"city":"Raka","region":"45.9297","cords":"45.9297,15.3842"},{"city":"Škocjan","region":"45.9067","cords":"45.9067,15.2914"},{"city":"Bučka","region":"45.9333","cords":"45.9333,15.3167"},{"city":"Brestanica","region":"45.9953","cords":"45.9953,15.4775"},{"city":"Senovo","region":"46.0236","cords":"46.0236,15.4769"},{"city":"Koprivnica","region":"46.0353","cords":"46.0353,15.5403"},{"city":"Blanca","region":"45.9833","cords":"45.9833,15.4"},{"city":"Sevnica","region":"46.0078","cords":"46.0078,15.3156"},{"city":"Zabukovje","region":"46.055","cords":"46.055,15.3675"},{"city":"Studenec","region":"45.9667","cords":"45.9667,15.35"},{"city":"Boštanj","region":"46.0144","cords":"46.0144,15.2825"},{"city":"Tržišče","region":"45.9589","cords":"45.9589,15.1972"},{"city":"Krmelj","region":"45.9847","cords":"45.9847,15.1894"},{"city":"Šentjanž","region":"46.0114","cords":"46.0114,15.1672"},{"city":"Šentjernej","region":"45.84","cords":"45.84,15.3361"},{"city":"Kostanjevica na Krki","region":"45.8461","cords":"45.8461,15.4222"},{"city":"Podbočje","region":"45.8667","cords":"45.8667,15.4667"},{"city":"Brusnice","region":"45.7514","cords":"45.7514,15.1715"},{"city":"Stopiče","region":"45.7694","cords":"45.7694,15.2097"},{"city":"Uršna sela","region":"45.7333","cords":"45.7333,15.1333"},{"city":"Metlika","region":"45.6472","cords":"45.6472,15.3142"},{"city":"Suhor","region":"45.5296","cords":"45.5296,14.8708"},{"city":"Gradac","region":"45.6167","cords":"45.6167,15.25"},{"city":"Semič","region":"45.6461","cords":"45.6461,15.1822"},{"city":"Črnomelj","region":"45.5711","cords":"45.5711,15.1889"},{"city":"Adlešiči","region":"45.5222","cords":"45.5222,15.3065"},{"city":"Stari trg ob Kolpi","region":"45.4936","cords":"45.4936,15.0772"},{"city":"Dragatuš","region":"45.5208","cords":"45.5208,15.1756"},{"city":"Vinica","region":"45.4601","cords":"45.4601,15.254"},{"city":"Dolenjske Toplice","region":"45.7566","cords":"45.7566,15.0592"},{"city":"Straža","region":"45.78","cords":"45.78,15.0728"},{"city":"Žužemberk","region":"45.8339","cords":"45.8339,14.9292"},{"city":"Dvor","region":"45.8139","cords":"45.8139,14.9711"},{"city":"Hinje","region":"45.7656","cords":"45.7656,14.8822"},{"city":"Novo mesto","region":"45.804","cords":"45.804,15.1689"},{"city":"Novo mesto","region":"45.804","cords":"45.804,15.1689"},{"city":"Murska Sobota - dostava","region":"46.6586","cords":"46.6586,16.162"},{"city":"Murska Sobota - poštni predali","region":"46.6612","cords":"46.6612,16.1651"},{"city":"Puconci","region":"46.7067","cords":"46.7067,16.1564"},{"city":"Mačkovci","region":"46.7814","cords":"46.7814,16.1689"},{"city":"Petrovci","region":"46.8053","cords":"46.8053,16.2225"},{"city":"Šalovci","region":"46.825","cords":"46.825,16.2981"},{"city":"Hodoš/Hodos","region":"46.7688","cords":"46.7688,16.2396"},{"city":"Križevci","region":"46.7889","cords":"46.7889,16.2469"},{"city":"Prosenjakovci/Partosfalva","region":"46.7408","cords":"46.7408,16.3175"},{"city":"Fokovci","region":"46.7333","cords":"46.7333,16.2667"},{"city":"Lendava/Lendva","region":"46.655","cords":"46.655,16.2946"},{"city":"Martjanci","region":"46.6864","cords":"46.6864,16.1978"},{"city":"Bogojina","region":"46.6761","cords":"46.6761,16.2839"},{"city":"Dobrovnik/Dobronak","region":"46.655","cords":"46.655,16.2946"},{"city":"Turnišče","region":"46.6278","cords":"46.6278,16.3203"},{"city":"Velika Polana","region":"46.5719","cords":"46.5719,16.3469"},{"city":"Moravske Toplice","region":"46.6831","cords":"46.6831,16.2208"},{"city":"Kobilje","region":"46.6847","cords":"46.6847,16.3978"},{"city":"Beltinci","region":"46.6053","cords":"46.6053,16.2406"},{"city":"Črenšovci","region":"46.5744","cords":"46.5744,16.2906"},{"city":"Odranci","region":"46.5867","cords":"46.5867,16.2803"},{"city":"Ljutomer","region":"46.5208","cords":"46.5208,16.1975"},{"city":"Veržej","region":"46.5836","cords":"46.5836,16.1653"},{"city":"Križevci pri Ljutomeru","region":"46.5683","cords":"46.5683,16.1386"},{"city":"Mala Nedelja","region":"46.5289","cords":"46.5289,16.0558"},{"city":"Sv. Jurij ob Ščavnici","region":"46.5594","cords":"46.5594,16.1077"},{"city":"Spodnji Ivanjci","region":"46.5956","cords":"46.5956,15.9814"},{"city":"Gornja Radgona","region":"46.6733","cords":"46.6733,15.9922"},{"city":"Tišina","region":"46.6836","cords":"46.6836,16.0525"},{"city":"Radenci","region":"46.642","cords":"46.642,16.0378"},{"city":"Apače","region":"46.6972","cords":"46.6972,15.9106"},{"city":"Cankova","region":"46.7208","cords":"46.7208,16.0225"},{"city":"Rogašovci","region":"46.8","cords":"46.8,16.0333"},{"city":"Kuzma","region":"46.8369","cords":"46.8369,16.0833"},{"city":"Grad","region":"46.8","cords":"46.8,16.1"},{"city":"Bodonci","region":"46.7442","cords":"46.7442,16.0922"},{"city":"Murska Sobota","region":"46.6625","cords":"46.6625,16.1664"},{"city":"Radenci","region":"46.642","cords":"46.642,16.0378"},{"city":"Murska Sobota","region":"46.6625","cords":"46.6625,16.1664"}]